rxvc
