Metadata-Version: 1.0
Name: rxvc
Version: 0.1.1
Summary: Command line utility for controlling Yamaha receivers.
Home-page: https://github.com/raynes/rxvc
Author: Anthony Grimes
Author-email: i@raynes.me
License: MIT
Platform: UNKNOWN
